{".class": "MypyFile", "_fullname": "GUItest", "is_partial_stub_package": false, "is_stub": false, "names": {".class": "SymbolTable", "Figure": {".class": "SymbolTableNode", "kind": "Gdef", "node": {".class": "Var", "flags": ["is_suppressed_import", "is_ready"], "fullname": "GUItest.Figure", "name": "Figure", "type": {".class": "AnyType", "missing_import_name": "GUItest.Figure", "source_any": null, "type_of_any": 3}}}, "FigureCanvas": {".class": "SymbolTableNode", "kind": "Gdef", "node": {".class": "Var", "flags": ["is_suppressed_import", "is_ready"], "fullname": "GUItest.FigureCanvas", "name": "FigureCanvas", "type": {".class": "AnyType", "missing_import_name": "GUItest.FigureCanvas", "source_any": null, "type_of_any": 3}}}, "NavigationToolbar": {".class": "SymbolTableNode", "kind": "Gdef", "node": {".class": "Var", "flags": ["is_suppressed_import", "is_ready"], "fullname": "GUItest.NavigationToolbar", "name": "NavigationToolbar", "type": {".class": "AnyType", "missing_import_name": "GUItest.NavigationToolbar", "source_any": null, "type_of_any": 3}}}, "QMainWindow": {".class": "SymbolTableNode", "kind": "Gdef", "node": {".class": "Var", "flags": [], "fullname": "GUItest.QMainWindow", "name": "QMainWindow", "type": {".class": "AnyType", "missing_import_name": "GUItest.loadUiType", "source_any": {".class": "AnyType", "missing_import_name": "GUItest.loadUiType", "source_any": null, "type_of_any": 3}, "type_of_any": 7}}}, "Ui_MainWindow": {".class": "SymbolTableNode", "kind": "Gdef", "node": {".class": "Var", "flags": [], "fullname": "GUItest.Ui_MainWindow", "name": "Ui_MainWindow", "type": {".class": "AnyType", "missing_import_name": "GUItest.loadUiType", "source_any": {".class": "AnyType", "missing_import_name": "GUItest.loadUiType", "source_any": null, "type_of_any": 3}, "type_of_any": 7}}}, "__doc__": {".class": "SymbolTableNode", "kind": "Gdef", "node": {".class": "Var", "flags": ["is_ready"], "fullname": "GUItest.__doc__", "name": "__doc__", "type": "builtins.str"}}, "__file__": {".class": "SymbolTableNode", "kind": "Gdef", "node": {".class": "Var", "flags": ["is_ready"], "fullname": "GUItest.__file__", "name": "__file__", "type": "builtins.str"}}, "__name__": {".class": "SymbolTableNode", "kind": "Gdef", "node": {".class": "Var", "flags": ["is_ready"], "fullname": "GUItest.__name__", "name": "__name__", "type": "builtins.str"}}, "__package__": {".class": "SymbolTableNode", "kind": "Gdef", "node": {".class": "Var", "flags": ["is_ready"], "fullname": "GUItest.__package__", "name": "__package__", "type": "builtins.str"}}, "loadUiType": {".class": "SymbolTableNode", "kind": "Gdef", "node": {".class": "Var", "flags": ["is_suppressed_import", "is_ready"], "fullname": "GUItest.loadUiType", "name": "loadUiType", "type": {".class": "AnyType", "missing_import_name": "GUItest.loadUiType", "source_any": null, "type_of_any": 3}}}}, "path": "h:\\L330backup\\file\\work_index\\generalfile\\github\\noloadcharacteristic\\GUItest.py"}